wirepas_networktool_messaging/__about__.py
wirepas_networktool_messaging/__init__.py
wirepas_networktool_messaging/__main__.py
wirepas_networktool_messaging/proto/__init__.py
wirepas_networktool_messaging/proto/commons_pb2.py
wirepas_networktool_messaging/proto/internal_pb2.py
wirepas_networktool_messaging/proto/message_pb2.py
wirepas_networktool_messaging/proto/nanopb_pb2.py
wirepas_networktool_messaging/proto/otap_pb2.py
wirepas_networktool_messaging/proto/positioning_pb2.py
wirepas_networktool_messaging/proto/remote_api_pb2.py
wirepas_networktool_messaging-4.4.3.dist-info/LICENSE
wirepas_networktool_messaging-4.4.3.dist-info/METADATA
wirepas_networktool_messaging-4.4.3.dist-info/WHEEL
wirepas_networktool_messaging-4.4.3.dist-info/top_level.txt
wirepas_networktool_messaging-4.4.3.dist-info/RECORD
