Metadata-Version: 2.1
Name: wirepas-networktool-messaging
Version: 4.4.3
Summary: WNT protocol buffers bindings.
Home-page: https://github.com/wirepas/wirepas-networktool-messaging-python
Author: Wirepas Ltd
Author-email: opensource@wirepas.com
License: Apache-2
Keywords: wirepas WNT
Classifier: Development Status :: 5 - Production/Stable
Classifier: Intended Audience :: Developers
Classifier: License :: OSI Approved :: Apache Software License
Classifier: Topic :: Software Development :: Libraries
Classifier: Programming Language :: Python :: 3
License-File: LICENSE
Requires-Dist: protobuf<4.0,>=3.12.2
